disseminate/__init__.py
disseminate/__version__.py
disseminate/settings.py
disseminate/software_dependencies.py
disseminate/attributes/__init__.py
disseminate/attributes/attributes.py
disseminate/builders/__init__.py
disseminate/builders/asy_builders.py
disseminate/builders/builder.py
disseminate/builders/copy.py
disseminate/builders/environment.py
disseminate/builders/exceptions.py
disseminate/builders/executor.py
disseminate/builders/imagemagick.py
disseminate/builders/jinja_render.py
disseminate/builders/latexmk.py
disseminate/builders/pdf2svg.py
disseminate/builders/pdfcrop.py
disseminate/builders/pdflatex.py
disseminate/builders/pdfrender.py
disseminate/builders/save_temp.py
disseminate/builders/scalesvg.py
disseminate/builders/svgrender.py
disseminate/builders/utils.py
disseminate/builders/validators.py
disseminate/builders/xhtml2epub.py
disseminate/builders/composite_builders/__init__.py
disseminate/builders/composite_builders/composite_builder.py
disseminate/builders/composite_builders/parallel_builder.py
disseminate/builders/composite_builders/sequential_builder.py
disseminate/builders/deciders/__init__.py
disseminate/builders/deciders/decider.py
disseminate/builders/deciders/md5decider.py
disseminate/builders/deciders/utils_hash.py
disseminate/builders/scanners/__init__.py
disseminate/builders/scanners/html_scanner.py
disseminate/builders/scanners/scanner.py
disseminate/builders/target_builders/__init__.py
disseminate/builders/target_builders/epub_builder.py
disseminate/builders/target_builders/exceptions.py
disseminate/builders/target_builders/html_builder.py
disseminate/builders/target_builders/pdf_builder.py
disseminate/builders/target_builders/receivers.py
disseminate/builders/target_builders/signals.py
disseminate/builders/target_builders/target_builder.py
disseminate/builders/target_builders/tex_builder.py
disseminate/builders/target_builders/txt_builder.py
disseminate/builders/target_builders/xhtml_builder.py
disseminate/checkers/__init__.py
disseminate-2.3.9.dist-info/LICENSE
disseminate-2.3.9.dist-info/METADATA
disseminate-2.3.9.dist-info/WHEEL
disseminate-2.3.9.dist-info/entry_points.txt
disseminate-2.3.9.dist-info/top_level.txt
disseminate-2.3.9.dist-info/RECORD
