Metadata-Version: 2.1
Name: disseminate
Version: 2.3.9
Summary: A document processor and generation engine
Home-page: https://docs.dissemia.org/projects/disseminate/en/latest
Author: Justin L Lorieau, Dissemia Foundation
License: AGPLv3
Project-URL: Documentation, https://docs.dissemia.org/projects/disseminate/en/latest
Project-URL: GitHub Project, https://github.com/dissemia/disseminate
Project-URL: Issue Tracker, https://github.com/dissemia/disseminate/issues
Keywords: document processor academic publishing
Platform: UNKNOWN
Classifier: Development Status :: 5 - Production/Stable
Classifier: Intended Audience :: End Users/Desktop
Classifier: Intended Audience :: Science/Research
Classifier: Operating System :: MacOS :: MacOS X
Classifier: Operating System :: POSIX :: Linux
Classifier: Programming Language :: Python
Classifier: Programming Language :: Python :: 3
Classifier: Programming Language :: Python :: 3.7
Classifier: Programming Language :: Python :: 3.8
Classifier: Programming Language :: Python :: 3.9
Classifier: Topic :: Text Processing
Classifier: Topic :: Text Processing :: General
Classifier: Topic :: Text Processing :: Markup
Classifier: Topic :: Text Processing :: Markup :: HTML
Classifier: Topic :: Text Processing :: Markup :: LaTeX
Classifier: Topic :: Internet :: WWW/HTTP :: Site Management
Classifier: Topic :: Software Development :: Documentation
Requires-Dist: regex (>=2018.11.22)
Requires-Dist: jinja2 (>=3.0)
Requires-Dist: lxml (>=4.3.0)
Requires-Dist: python-slugify (>=2.0.1)
Requires-Dist: pdfCropMargins (>=0.1.4)
Requires-Dist: click (>=7.0)
Requires-Dist: tornado (>=6.1)
Requires-Dist: pygments (>=2.6)
Requires-Dist: diskcache (>=4.1)
Requires-Dist: pathvalidate (>=2.2)
Provides-Extra: dev
Requires-Dist: sphinx ; extra == 'dev'
Requires-Dist: sphinx-rtd-theme ; extra == 'dev'
Requires-Dist: sphinx-click ; extra == 'dev'
Requires-Dist: numpydoc ; extra == 'dev'
Requires-Dist: asv ; extra == 'dev'
Provides-Extra: termcolor
Requires-Dist: termcolor ; extra == 'termcolor'
Provides-Extra: test
Requires-Dist: pytest ; extra == 'test'
Requires-Dist: pytest-cov ; extra == 'test'
Requires-Dist: tox ; extra == 'test'
Requires-Dist: coverage ; extra == 'test'
Requires-Dist: flake8 ; extra == 'test'
Requires-Dist: epubcheck (>=0.4) ; extra == 'test'
